[
  {
    "id": 202,
    "journalId": 83,
    "accountId": 30,
    "debit": 10000,
    "credit": 0,
    "balance": 10000,
    "clientId": null,
    "description": "إيداع نقدي لرأس المال"
  },
  {
    "id": 203,
    "journalId": 83,
    "accountId": 59,
    "debit": 0,
    "credit": 10000,
    "balance": 10000,
    "clientId": null,
    "description": "رأس مال محمد"
  },
  {
    "id": 204,
    "journalId": 84,
    "accountId": 30,
    "debit": 15000,
    "credit": 0,
    "balance": 15000,
    "clientId": null,
    "description": "إيداع نقدي لرأس المال"
  },
  {
    "id": 205,
    "journalId": 84,
    "accountId": 61,
    "debit": 0,
    "credit": 15000,
    "balance": 15000,
    "clientId": null,
    "description": "رأس مال youssef"
  },
  {
    "id": 206,
    "journalId": 85,
    "accountId": 46,
    "debit": 10000,
    "credit": 0,
    "balance": 10000,
    "clientId": 1,
    "description": "Loan receivable"
  },
  {
    "id": 207,
    "journalId": 85,
    "accountId": 30,
    "debit": 0,
    "credit": 10000,
    "balance": -10000,
    "clientId": null,
    "description": "Bank disbursement"
  },
  {
    "id": 208,
    "journalId": 86,
    "accountId": 30,
    "debit": 3000,
    "credit": 0,
    "balance": 3000,
    "clientId": null,
    "description": "Repayment received from youssef khaled"
  },
  {
    "id": 209,
    "journalId": 86,
    "accountId": 46,
    "debit": 0,
    "credit": 2500,
    "balance": -2500,
    "clientId": 1,
    "description": "Loan principal repayment"
  },
  {
    "id": 210,
    "journalId": 86,
    "accountId": 47,
    "debit": 0,
    "credit": 500,
    "balance": 500,
    "clientId": null,
    "description": "Loan interest income"
  },
  {
    "id": 211,
    "journalId": 87,
    "accountId": 30,
    "debit": 8000,
    "credit": 0,
    "balance": 8000,
    "clientId": null,
    "description": "استلام سداد مبكر من العميل youssef khaled"
  },
  {
    "id": 212,
    "journalId": 87,
    "accountId": 46,
    "debit": 0,
    "credit": 7500,
    "balance": -7500,
    "clientId": 1,
    "description": "سداد أصل السلفة بالكامل"
  },
  {
    "id": 213,
    "journalId": 87,
    "accountId": 47,
    "debit": 0,
    "credit": 500,
    "balance": 500,
    "clientId": null,
    "description": "دخل الفائدة بعد خصم السداد المبكر"
  }
]